NPMpy/__init__.py
NPMpy/curate.py
NPMpy-0.1.6.dist-info/LICENSE
NPMpy-0.1.6.dist-info/METADATA
NPMpy-0.1.6.dist-info/WHEEL
NPMpy-0.1.6.dist-info/top_level.txt
NPMpy-0.1.6.dist-info/RECORD
