Metadata-Version: 2.1
Name: NPMpy
Version: 0.1.6
Summary: Curate Neurophotometrics data for pMat.
Home-page: https://github.com/MicTott/NPMpy
Author: Michael Totty
Author-email: MicTott@gmail.com
License: MIT License
Platform: UNKNOWN
